{
  "airplane": [
    "a copilot",
    "a flight attendant",
    "a large, metal body",
    "a passenger",
    "a pilot",
    "a runway",
    "a tail",
    "engines",
    "engines on the wings",
    "landing gear",
    "object",
    "wings"
  ],
  "automobile": [
    "a dashboard",
    "a driver",
    "a large, metal body",
    "a passenger",
    "a pedal",
    "a road",
    "a seatbelt",
    "a steering wheel",
    "a tire",
    "a windshield",
    "an engine",
    "four round, black tires",
    "machine",
    "object",
    "side windows",
    "taillights",
    "transportation"
  ],
  "bird": [
    "a beak",
    "a bird feeder",
    "a birdfeeder",
    "a birdhouse",
    "a branch",
    "a cage",
    "a leaf",
    "a nest",
    "a tree",
    "a worm",
    "animal",
    "feathers",
    "living thing",
    "the ability to fly",
    "vertebrate",
    "wings"
  ],
  "cat": [
    "a cat bed",
    "a cat food dish",
    "a cat toy",
    "a litter box",
    "a scratching post",
    "a small, lithe body",
    "a tail",
    "animal",
    "four legs",
    "fur",
    "mammal",
    "pointed ears",
    "vertebrate",
    "whiskers"
  ],
  "deer": [
    "a Hunter",
    "a deer stand",
    "a field",
    "a forest",
    "a long neck",
    "a reddish-brown coat",
    "a rifle",
    "animal",
    "antlers",
    "grass",
    "hooves",
    "large, brown eyes",
    "long ears",
    "long, thin legs",
    "mammal",
    "nature",
    "trees",
    "vertebrate",
    "white spots on the coat",
    "woods"
  ],
  "dog": [
    "a collar",
    "a dog bowl",
    "a food bowl",
    "a four-legged mammal",
    "a leash",
    "a nose",
    "a person",
    "a tail",
    "a toy",
    "a wet nose",
    "animal",
    "food",
    "four legs",
    "fur",
    "living thing",
    "mammal",
    "organism",
    "pointed ears",
    "vertebrate"
  ],
  "frog": [
    "a beetle",
    "a fly",
    "a green or brown body",
    "a lily pad",
    "a mosquito",
    "a person",
    "a pond",
    "a spider",
    "a wide mouth",
    "amphibian",
    "animal",
    "insects",
    "large, bulging eyes",
    "lily pads",
    "long hind legs for jumping",
    "vertebrate",
    "webbed feet"
  ],
  "horse": [
    "a barn",
    "a bridle",
    "a halter",
    "a large body",
    "a lead rope",
    "a long neck",
    "a mane and tail",
    "a pasture",
    "a reins",
    "a rider",
    "a saddle",
    "animal",
    "four legs",
    "hooves",
    "mammal",
    "quadruped",
    "vertebrate"
  ],
  "ship": [
    "a boat",
    "a captain",
    "a deck",
    "a dock",
    "a large size",
    "a pointed front end",
    "a port",
    "a rudder",
    "cargo",
    "large sails or engines",
    "multiple sails",
    "object",
    "the ocean",
    "transportation",
    "vessel",
    "watercraft"
  ],
  "truck": [
    "a bed for carrying cargo",
    "a cab for the driver",
    "a dashboard",
    "a driver",
    "a gear shift",
    "a grille",
    "a hitch",
    "a large, rectangular body",
    "a road",
    "a seatbelt",
    "a steering wheel",
    "a tire",
    "a trailer",
    "four wheels",
    "object",
    "transportation",
    "two headlights"
  ]
}
